[
  {
    "activity": "50+ swim",
    "start_time": null,
    "end_time": null,
    "period_start_date": "2026-01-05",
    "period_end_date": "2026-03-15",
    "day_of_week": 6,
    "facility": "CARDELREC Recreation Complex Goulbourn"
  },
  {
    "activity": "50+ swim",
    "start_time": null,
    "end_time": null,
    "period_start_date": "2026-01-05",
    "period_end_date": "2026-03-15",
    "day_of_week": 7,
    "facility": "CARDELREC Recreation Complex Goulbourn"
  },
  {
    "activity": "Public swim with no slide",
    "start_time": null,
    "end_time": null,
    "period_start_date": "2026-01-05",
    "period_end_date": "2026-03-15",
    "day_of_week": 2,
    "facility": "CARDELREC Recreation Complex Goulbourn"
  },
  {
    "activity": "Public swim with no slide",
    "start_time": null,
    "end_time": null,
    "period_start_date": "2026-01-05",
    "period_end_date": "2026-03-15",
    "day_of_week": 4,
    "facility": "CARDELREC Recreation Complex Goulbourn"
  },
  {
    "activity": "Public swim with no slide",
    "start_time": null,
    "end_time": null,
    "period_start_date": "2026-01-05",
    "period_end_date": "2026-03-15",
    "day_of_week": 6,
    "facility": "CARDELREC Recreation Complex Goulbourn"
  },
  {
    "activity": "Public swim with no slide",
    "start_time": null,
    "end_time": null,
    "period_start_date": "2026-01-05",
    "period_end_date": "2026-03-15",
    "day_of_week": 7,
    "facility": "CARDELREC Recreation Complex Goulbourn"
  },
  {
    "activity": "Aquafit General - Shallow/deep combo",
    "start_time": null,
    "end_time": null,
    "period_start_date": "2026-01-05",
    "period_end_date": "2026-03-15",
    "day_of_week": 6,
    "facility": "CARDELREC Recreation Complex Goulbourn"
  },
  {
    "activity": "Aquafit General - Shallow/deep combo",
    "start_time": null,
    "end_time": null,
    "period_start_date": "2026-01-05",
    "period_end_date": "2026-03-15",
    "day_of_week": 7,
    "facility": "CARDELREC Recreation Complex Goulbourn"
  }
]