[
  {
    "activity": "Pickleball 16+",
    "start_time": null,
    "end_time": null,
    "period_start_date": "2026-01-05",
    "period_end_date": "2026-06-21",
    "day_of_week": 6,
    "facility": "François Dupuis Recreation Centre"
  },
  {
    "activity": "Basketball 12+",
    "start_time": null,
    "end_time": null,
    "period_start_date": "2026-01-05",
    "period_end_date": "2026-06-21",
    "day_of_week": 6,
    "facility": "François Dupuis Recreation Centre"
  },
  {
    "activity": "Basketball - Parent with Child (ages 12 and under)",
    "start_time": null,
    "end_time": null,
    "period_start_date": "2026-01-05",
    "period_end_date": "2026-06-21",
    "day_of_week": 6,
    "facility": "François Dupuis Recreation Centre"
  }
]